drax
