Metadata-Version: 1.0
Name: drax
Version: 0.4.0
Summary: Drax is a react and python implementation of the dashingdashboard
Home-page: http://github.com/tax/drax
Author: tax
Author-email: paultax@gmail.com
License: MIT
Platform: UNKNOWN
